instack/__init__.py
instack/element.py
instack/main.py
instack/runner.py
instack/tests/__init__.py
instack/tests/test_runner.py
instack/tests/elements/dep1/install.d/50-dep1
instack/tests/elements/dep2/element-deps
instack/tests/elements/dep2/install.d/50-dep2
instack/tests/elements/echo/install.d/50-echo
instack/tests/elements/error/install.d/50-error
instack/tests/elements/os/element-provides
instack/tests/elements/output/install.d/50-output
instack/tests/elements/repo/source-repository-repo
instack-9.1.0.dist-info/METADATA
instack-9.1.0.dist-info/RECORD
instack-9.1.0.dist-info/WHEEL
instack-9.1.0.dist-info/entry_points.txt
instack-9.1.0.dist-info/pbr.json
instack-9.1.0.dist-info/top_level.txt
